setup.py
deephit_probability/Binomialdistribution.py
deephit_probability/Gaussiandistribution.py
deephit_probability/Generaldistribution.py
deephit_probability/__init__.py
deephit_probability.egg-info/PKG-INFO
deephit_probability.egg-info/SOURCES.txt
deephit_probability.egg-info/dependency_links.txt
deephit_probability.egg-info/not-zip-safe
deephit_probability.egg-info/top_level.txt