Metadata-Version: 1.0
Name: deephit-probability
Version: 1.1
Summary: gaussian and binomial distribution
Home-page: UNKNOWN
Author: Deepak Rajpurohit
Author-email: ait.17bcs4172@gmail.com
License: UNKNOWN
Platform: UNKNOWN
